{
  "reportTitle": "鉄道本部報 乙 第 0146 号の 17",
  "mainTitle": "回送列車の運転について",
  "description": "重要部検査入場に伴い、下記のとおり回送列車を運転する。",
  "details": {
    "date": "2025年 8月 14日 (木)",
    "runNumber": "89N",
    "formation": {
      "length": "8両編成",
      "cars": [
        "7502-8",
        "7502-7",
        "7502-6",
        "7502-5",
        "7502-4",
        "7502-3",
        "7502-2",
        "7502-1号車"
      ]
    },
    "supervisor": null,
    "itinerary": [
      { "station": "高砂", "track": "2T", "time": "13:57" },
      { "station": "東中山", "track": null, "time": "14:06" },
      { "station": "佐倉", "track": null, "time": "15:00" },
      { "station": "宗吾参道", "track": "1T", "time": "15:11" }
    ],
    "notes": [
      "第1312列車、高砂2T→1Tに変更する。",
      "列車種別表示は「８」表示とする。",
      "TTC設定可。"
    ]
  }
}
