{
  "ok": true,
  "announcementDate": "2026年7月21日",
  "asOf": "18時現在",
  "title": "近畿、東北、中国地区における輸送障害に伴う列車遅延について",
  "incidents": [
    {
      "time": "2026年7月21日(火)0時28分～2時28分",
      "detail": "山陽線 手柄山平和公園～英賀保駅間(兵庫県) 人身事故(遅れ)"
    },
    {
      "time": "2026年7月21日(火)3時10分～4時28分",
      "detail": "東海道線 河瀬～能登川駅間(滋賀県) 動物と列車の接触(遅れ)"
    },
    {
      "time": "2026年7月21日(火)11時01分～11時13分",
      "detail": "東北線 花巻空港～花巻駅間(岩手県) 踏切支障(遅れ)"
    },
    {
      "time": "2026年7月21日(火)15時58分～16時12分",
      "detail": "山陽線 西川原～岡山駅間(岡山県) 踏切支障(遅れ)"
    }
  ],
  "routes": [
    {
      "name": "東海道・山陽線 下り",
      "trains": [
        {
          "service": "20日発1063列車(名古屋タ→熊本)",
          "location": "終 着",
          "status": "+3時間16分",
          "route": "東海道・山陽線 下り"
        },
        {
          "service": "20日発1091列車(沼津→福岡タ)",
          "location": "終 着",
          "status": "+52分",
          "route": "東海道・山陽線 下り"
        }
      ]
    },
    {
      "name": "東海道・山陽線 上り",
      "trains": [
        {
          "service": "21日発5054列車(新南陽→東京タ)",
          "location": "吹田タ",
          "status": "+43分着予定",
          "route": "東海道・山陽線 上り"
        }
      ]
    },
    {
      "name": "東北・函館線 上り",
      "trains": [
        {
          "service": "21日発3050列車(札幌タ→隅田川)",
          "location": "終 着",
          "status": "+1時間52分予定",
          "route": "東北・函館線 上り"
        }
      ]
    }
  ],
  "trains": [
    {
      "service": "20日発1063列車(名古屋タ→熊本)",
      "location": "終 着",
      "status": "+3時間16分",
      "route": "東海道・山陽線 下り"
    },
    {
      "service": "20日発1091列車(沼津→福岡タ)",
      "location": "終 着",
      "status": "+52分",
      "route": "東海道・山陽線 下り"
    },
    {
      "service": "21日発5054列車(新南陽→東京タ)",
      "location": "吹田タ",
      "status": "+43分着予定",
      "route": "東海道・山陽線 上り"
    },
    {
      "service": "21日発3050列車(札幌タ→隅田川)",
      "location": "終 着",
      "status": "+1時間52分予定",
      "route": "東北・函館線 上り"
    }
  ],
  "fetchedLabel": "2026年7月21日 18:14 JST",
  "source": "https://www.jrfreight.co.jp/i_daiya.html",
  "mirror": "https://tayunet-traininfo.com/JRF_status/index.html",
  "proxiedAt": "2026-07-21T11:15:36.513Z"
}
